Metadata-Version: 2.1
Name: classmapper
Version: 0.0.1
Summary: UNKNOWN
Home-page: https://github.com/David-Lor/python-classmapper
Author: David Lorenzo
Author-email: 17401854+David-Lor@users.noreply.github.com
License: ISC
Download-URL: https://github.com/David-Lor/python-classmapper/archive/main.zip
Keywords: classmapper,objectmapper,class-mapper,object-mapper,mapping,mapper,mapstructs
Platform: UNKNOWN
Classifier: Development Status :: 4 - Beta
Classifier: Intended Audience :: Developers
Classifier: Topic :: Software Development :: Libraries
Classifier: License :: OSI Approved :: ISC License (ISCL)
Classifier: Programming Language :: Python :: 3.8
Classifier: Programming Language :: Python :: 3.9
Classifier: Programming Language :: Python :: 3.10
Classifier: Programming Language :: Python :: 3.11
License-File: LICENSE.md
